pydra/tasks/fsl/__init__.py
pydra/tasks/fsl/fast.py
pydra/tasks/fsl/maths.py
pydra/tasks/fsl/susan.py
pydra/tasks/fsl/bet/__init__.py
pydra/tasks/fsl/bet/bet.py
pydra/tasks/fsl/bet/robustfov.py
pydra/tasks/fsl/eddy/__init__.py
pydra/tasks/fsl/eddy/applytopup.py
pydra/tasks/fsl/eddy/eddy.py
pydra/tasks/fsl/eddy/topup.py
pydra/tasks/fsl/flirt/__init__.py
pydra/tasks/fsl/flirt/convertxfm.py
pydra/tasks/fsl/flirt/flirt.py
pydra/tasks/fsl/flirt/img2imgcoord.py
pydra/tasks/fsl/flirt/img2stdcoord.py
pydra/tasks/fsl/flirt/specs.py
pydra/tasks/fsl/flirt/std2imgcoord.py
pydra/tasks/fsl/fnirt/__init__.py
pydra/tasks/fsl/fnirt/applywarp.py
pydra/tasks/fsl/fnirt/convertwarp.py
pydra/tasks/fsl/fnirt/fnirt.py
pydra/tasks/fsl/fnirt/fnirtfileutils.py
pydra/tasks/fsl/fnirt/invwarp.py
pydra/tasks/fsl/fnirt/specs.py
pydra/tasks/fsl/fugue/__init__.py
pydra/tasks/fsl/fugue/fugue.py
pydra/tasks/fsl/fugue/prelude.py
pydra/tasks/fsl/fugue/prepare_fieldmap.py
pydra/tasks/fsl/fugue/sigloss.py
pydra/tasks/fsl/utils/__init__.py
pydra/tasks/fsl/utils/chfiletype.py
pydra/tasks/fsl/utils/fft.py
pydra/tasks/fsl/utils/info.py
pydra/tasks/fsl/utils/interleave.py
pydra/tasks/fsl/utils/merge.py
pydra/tasks/fsl/utils/orient.py
pydra/tasks/fsl/utils/reorient2std.py
pydra/tasks/fsl/utils/roi.py
pydra/tasks/fsl/utils/selectvols.py
pydra/tasks/fsl/utils/smoothfill.py
pydra/tasks/fsl/utils/split.py
pydra/tasks/fsl/utils/swapdim.py
clinica_pydra_fsl-0.1.0.dist-info/METADATA
clinica_pydra_fsl-0.1.0.dist-info/WHEEL
clinica_pydra_fsl-0.1.0.dist-info/licenses/LICENSE
clinica_pydra_fsl-0.1.0.dist-info/RECORD
